setup.py
neng/__init__.py
neng/cmaes.py
neng/game.py
neng/game_reader.py
neng/neng.py
neng/strategy_profile.py
neng/support_enumeration.py
neng.egg-info/PKG-INFO
neng.egg-info/SOURCES.txt
neng.egg-info/dependency_links.txt
neng.egg-info/entry_points.txt
neng.egg-info/requires.txt
neng.egg-info/top_level.txt