Metadata-Version: 1.0
Name: neng
Version: 0.1
Summary: A tool for computing Nash equilibria
Home-page: https://github.com/Artimi/neng
Author: Petr Šebek
Author-email: petrsebek1@gmail.com
License: MIT
Platform: UNKNOWN
